multichoicelib/__init__.py
multichoicelib/selection.sh
multichoicelib-0.0.3.dist-info/LICENSE
multichoicelib-0.0.3.dist-info/METADATA
multichoicelib-0.0.3.dist-info/WHEEL
multichoicelib-0.0.3.dist-info/top_level.txt
multichoicelib-0.0.3.dist-info/RECORD
