Metadata-Version: 2.1
Name: multichoicelib
Version: 0.0.3
Summary: Miniscule Python Module for multiple choice menus using arrow keys
Author-email: cph101 <cph101@icloud.com>
License: MIT
Project-URL: Documentation, https://github.com/cph101/MultiChoiceLib.py/tree/main#readme
Project-URL: Source, https://github.com/cph101/MultiChoiceLib.py
Project-URL: Tracker, https://github.com/cph101/MultiChoiceLib.py/issues
Requires-Python: >=3.8.1
License-File: LICENSE
